git_json_tree.py
git_json_tree-0.1.0.dev20180216.dist-info/DESCRIPTION.rst
git_json_tree-0.1.0.dev20180216.dist-info/METADATA
git_json_tree-0.1.0.dev20180216.dist-info/RECORD
git_json_tree-0.1.0.dev20180216.dist-info/WHEEL
git_json_tree-0.1.0.dev20180216.dist-info/entry_points.txt
git_json_tree-0.1.0.dev20180216.dist-info/metadata.json
git_json_tree-0.1.0.dev20180216.dist-info/top_level.txt
