Metadata-Version: 2.0
Name: git-json-tree
Version: 0.1.0.dev20180216
Summary: Git-JSON-Tree.
Home-page: http://github.com/jirikuncar/git-json-tree/
Author: Jiri Kuncar
Author-email: jiri.kuncar+gjt@gmail.com
License: MIT
Platform: any
Classifier: Intended Audience :: Developers
Classifier: License :: OSI Approved :: MIT License
Classifier: Operating System :: OS Independent
Classifier: Programming Language :: Python
Classifier: Topic :: Software Development :: Libraries :: Python Modules
Classifier: Programming Language :: Python :: 2
Classifier: Programming Language :: Python :: 2.7
Classifier: Programming Language :: Python :: 3
Classifier: Programming Language :: Python :: 3.4
Classifier: Programming Language :: Python :: 3.5
Classifier: Programming Language :: Python :: 3.6
Classifier: Development Status :: 1 - Planning
Requires-Dist: click (>=6.7)
Requires-Dist: dulwich (>=0.18.6)
Provides-Extra: all
Requires-Dist: Sphinx (>=1.6.6); extra == 'all'
Requires-Dist: check-manifest (>=0.25); extra == 'all'
Requires-Dist: coverage (>=4.0); extra == 'all'
Requires-Dist: coverage (>=4.0.0); extra == 'all'
Requires-Dist: isort (>=4.2.2); extra == 'all'
Requires-Dist: hypothesis (>=3.45.0); extra == 'all'
Requires-Dist: mock (>=1.0.0); extra == 'all'
Requires-Dist: pydocstyle (>=1.0.0); extra == 'all'
Requires-Dist: pytest-cache (>=1.0); extra == 'all'
Requires-Dist: pytest-cov (>=2.5.1); extra == 'all'
Requires-Dist: pytest-isort (>=0.1.0); extra == 'all'
Requires-Dist: pytest-pep8 (>=1.0.6); extra == 'all'
Requires-Dist: pytest (>=3.4.0); extra == 'all'
Requires-Dist: Sphinx (>=1.6.6); extra == 'all'
Requires-Dist: check-manifest (>=0.25); extra == 'all'
Requires-Dist: coverage (>=4.0); extra == 'all'
Requires-Dist: coverage (>=4.0.0); extra == 'all'
Requires-Dist: isort (>=4.2.2); extra == 'all'
Requires-Dist: hypothesis (>=3.45.0); extra == 'all'
Requires-Dist: mock (>=1.0.0); extra == 'all'
Requires-Dist: pydocstyle (>=1.0.0); extra == 'all'
Requires-Dist: pytest-cache (>=1.0); extra == 'all'
Requires-Dist: pytest-cov (>=2.5.1); extra == 'all'
Requires-Dist: pytest-isort (>=0.1.0); extra == 'all'
Requires-Dist: pytest-pep8 (>=1.0.6); extra == 'all'
Requires-Dist: pytest (>=3.4.0); extra == 'all'
Provides-Extra: docs
Requires-Dist: Sphinx (>=1.6.6); extra == 'docs'
Provides-Extra: tests
Requires-Dist: check-manifest (>=0.25); extra == 'tests'
Requires-Dist: coverage (>=4.0); extra == 'tests'
Requires-Dist: coverage (>=4.0.0); extra == 'tests'
Requires-Dist: isort (>=4.2.2); extra == 'tests'
Requires-Dist: hypothesis (>=3.45.0); extra == 'tests'
Requires-Dist: mock (>=1.0.0); extra == 'tests'
Requires-Dist: pydocstyle (>=1.0.0); extra == 'tests'
Requires-Dist: pytest-cache (>=1.0); extra == 'tests'
Requires-Dist: pytest-cov (>=2.5.1); extra == 'tests'
Requires-Dist: pytest-isort (>=0.1.0); extra == 'tests'
Requires-Dist: pytest-pep8 (>=1.0.6); extra == 'tests'
Requires-Dist: pytest (>=3.4.0); extra == 'tests'
